Metadata-Version: 1.1
Name: aioautomatic
Version: 0.6.3
Summary: Asyncio library for the Automatic API
Home-page: https://github.com/armills/aioautomatic
Author: Adam Mills
Author-email: adam@armills.info
License: Apache Software License 2.0
Keywords: aioautomatic
Platform: UNKNOWN
Classifier: Development Status :: 4 - Beta
Classifier: Intended Audience :: Developers
Classifier: License :: OSI Approved :: Apache Software License
Classifier: Natural Language :: English
Classifier: Programming Language :: Python :: 3
Classifier: Programming Language :: Python :: 3.4
Classifier: Programming Language :: Python :: 3.5
Classifier: Programming Language :: Python :: 3.6
